[{"Year":1985,"Value":0.0439439714},{"Year":1986,"Value":0.0652741514},{"Year":1987,"Value":0.0214762794},{"Year":1988,"Value":0.0211729833},{"Year":1989,"Value":0.0629273818},{"Year":1990,"Value":0.0},{"Year":1991,"Value":0.0},{"Year":1992,"Value":0.0851661805},{"Year":1993,"Value":0.0217412573},{"Year":1994,"Value":0.0},{"Year":1995,"Value":0.0229985511},{"Year":1996,"Value":0.0},{"Year":1997,"Value":0.0},{"Year":1998,"Value":0.0},{"Year":1999,"Value":0.0221970655},{"Year":2000,"Value":0.0},{"Year":2001,"Value":0.0},{"Year":2002,"Value":0.0211445547},{"Year":2003,"Value":0.0417562687},{"Year":2004,"Value":0.0},{"Year":2005,"Value":0.0},{"Year":2006,"Value":0.0},{"Year":2007,"Value":0.0},{"Year":2008,"Value":0.0},{"Year":2009,"Value":0.0},{"Year":2010,"Value":0.0206362145},{"Year":2011,"Value":0.0},{"Year":2012,"Value":0.0},{"Year":2013,"Value":0.0},{"Year":2014,"Value":0.0},{"Year":2015,"Value":0.0204735533},{"Year":2016,"Value":0.0},{"Year":2017,"Value":0.0},{"Year":2018,"Value":0.0},{"Year":2019,"Value":0.0},{"Year":2020,"Value":0.0381141137},{"Year":2021,"Value":0.0}]