{
  "resources": [
    {
      "path": "data.csv",
      "name": "data",
      "profile": "tabular-data-resource",
      "scheme": "file",
      "format": "csv",
      "hashing": "md5",
      "encoding": "utf-8",
      "schema": {
        "fields": [
          {
            "name": "Year",
            "type": "integer"
          },
          {
            "name": "data.mainsource",
            "type": "string",
            "constraints": {
              "enum": [
                "data.fuelcombustion",
                "data.bunkers",
                ""
              ]
            }
          },
          {
            "name": "source",
            "type": "string",
            "constraints": {
              "enum": [
                "data.energyindustries",
                "data.manufacturingindustriesandconstruction",
                "data.transportsector",
                "data.othersectors",
                "data.aviation",
                "Navigation",
                "data.navigation",
                ""
              ]
            }
          },
          {
            "name": "Value",
            "type": "number"
          }
        ]
      }
    }
  ],
  "profile": "data-package",
  "name": "9-4-1",
  "title": "CO2 emission per unit of value added"
}